ghanaweb/__init__.py
ghanaweb/scraper.py
ghanaweb/utils.py
myjoyonline/__init__.py
myjoyonline/scraper.py
myjoyonline/utils.py
ghanaweb_scraper-1.0.2.dist-info/METADATA
ghanaweb_scraper-1.0.2.dist-info/WHEEL
ghanaweb_scraper-1.0.2.dist-info/top_level.txt
ghanaweb_scraper-1.0.2.dist-info/RECORD
