Metadata-Version: 2.1
Name: ghanaweb-scraper
Version: 1.0.2
Summary: A python package to scrape data from GhanaWeb
Home-page: https://github.com/donwany/ghanaweb-scraper
Author: Theophilus Siameh
Author-email: theodondre@gmail.com
License: MIT License
Keywords: Scraper,Data,Ghanaweb,Web Scraper,Ghana Scraper
Platform: any
Classifier: Development Status :: 5 - Production/Stable
Classifier: Environment :: Console
Classifier: Intended Audience :: Developers
Classifier: Programming Language :: Python
Classifier: Programming Language :: Python :: 3
Classifier: Programming Language :: Python :: 3 :: Only
Classifier: Programming Language :: Python :: 3.7
Classifier: Programming Language :: Python :: 3.8
Classifier: Programming Language :: Python :: 3.9
Classifier: Programming Language :: Python :: 3.10
Classifier: Programming Language :: Python :: 3.11
Classifier: Programming Language :: Python :: Implementation :: CPython
Classifier: Programming Language :: Python :: Implementation :: PyPy
Classifier: Topic :: Software Development :: Libraries :: Python Modules
Classifier: Topic :: Software Development :: Testing
Classifier: Topic :: Utilities
Requires-Python: >=3.7
Requires-Dist: bs4
Requires-Dist: requests
